bisum/__init__.py
bisum/bisum.py
bisum/dense_intra.py
bisum/generic_functions.py
bisum/labels.py
bisum/sparse_intra.py
bisum/tensor_to_matrix.py
bisum/tensordot.py
bisum-0.2.0.dist-info/LICENSE
bisum-0.2.0.dist-info/METADATA
bisum-0.2.0.dist-info/WHEEL
bisum-0.2.0.dist-info/top_level.txt
bisum-0.2.0.dist-info/RECORD
