Metadata-Version: 2.1
Name: bisum
Version: 0.2.0
Summary: binary sparse and dense tensor partial-tracing
Author-email: Julio Candanedo <juliojcandanedo@gmail.com>
Maintainer-email: Julio Candanedo <juliojcandanedo@gmail.com>
License: MIT License
Project-URL: Source, https://github.com/jcandane/bisum
Keywords: pytorch,torch,tensors,Sparse Tensor,Sparse,contraction,partial-tracing,einsum,tensordot,attention
Classifier: Development Status :: 3 - Alpha
Classifier: Intended Audience :: Developers
Classifier: Intended Audience :: Science/Research
Classifier: License :: OSI Approved :: MIT License
Classifier: Programming Language :: Python :: 3
Classifier: Programming Language :: Python
Classifier: Programming Language :: Python :: 3.8
Classifier: Programming Language :: Python :: 3.9
Classifier: Programming Language :: Python :: 3.10
Classifier: Programming Language :: Python :: 3.11
Classifier: Operating System :: OS Independent
Classifier: Topic :: Scientific/Engineering
Classifier: Topic :: Software Development :: Libraries :: Python Modules
Requires-Python: >=3.8
License-File: LICENSE
Requires-Dist: torch
